{
  "1": {
    "file_id": "BQACAgUAAxkBAAICumgbabJdnrEHpcMs_O8VZjYYhIMPAALvEwACrVOxV1iWASD9dAtmNgQ",
    "file_name": "minecraft-1-21-72-music",
    "tags": [],
    "original_url": "https://t.me/minecraft_apk_downloadbot?start=1",
    "short_url": "https://t.me/minecraft_apk_downloadbot?start=1"
  },
  "2": {
    "file_id": "BQACAgUAAxkBAAICu2gbabLrP--VC3PCLVP8ERohf7cVAALwEwACrVOxV9Z-PxDm61quNgQ",
    "file_name": "minecraft-1-21-72",
    "tags": [],
    "original_url": "https://t.me/minecraft_apk_downloadbot?start=2",
    "short_url": "https://t.me/minecraft_apk_downloadbot?start=2"
  },
  "3": {
    "file_id": "BQACAgIAAxkBAAIC-WgbffIaNnqFQNCHGoE5OqT_kDN4AALYXQAC-gjJSm1oQJpbeDfANgQ",
    "file_name": "minecraft-1-21-51",
    "tags": [],
    "original_url": "https://t.me/minecraft_apk_downloadbot?start=3",
    "short_url": "https://t.me/minecraft_apk_downloadbot?start=3"
  },
  "4": {
    "file_id": "BQACAgIAAxkBAAIC-mgbffKxto1RC9BaG-WuHg9kg-KrAALXXQAC-gjJSnRUQEdUi8U6NgQ",
    "file_name": "minecraft-1-21-51-music",
    "tags": [],
    "original_url": "https://t.me/minecraft_apk_downloadbot?start=4",
    "short_url": "https://t.me/minecraft_apk_downloadbot?start=4"
  },
  "5": {
    "file_id": "BQACAgUAAxkBAAIC_2gbhJ4jQD2aIvznQ5tbuncpe7a9AAIeFAACvd1BV2TDcvlESj_KNgQ",
    "file_name": "minecraft-1-21-71-music",
    "tags": [],
    "original_url": "https://t.me/minecraft_apk_downloadbot?start=5",
    "short_url": "https://tfushorty.com/GJykHVk"
  },
  "6": {
    "file_id": "BQACAgUAAxkBAAIDAAFoG4SedugpM7P_OszBn1XifqLV8QACHxQAAr3dQVfDMik4hmhIuzYE",
    "file_name": "minecraft-1-21-71",
    "tags": [],
    "original_url": "https://t.me/minecraft_apk_downloadbot?start=6",
    "short_url": "https://tfushorty.com/kq9DyEg"
  }
}